obsea/__init__.py
obsea/ais.py
obsea/beamforming.py
obsea/core.py
obsea/datasets.py
obsea/gis.py
obsea/io.py
obsea/plot.py
obsea/processing.py
obsea/station.py
obsea/data/ais_cls.csv
obsea/data/ais_marine_traffic.csv
obsea/data/mmsi_list.csv
obsea/data/ship_length.csv
obsea/data/station_list.csv
obsea-0.0.3.dist-info/AUTHORS.rst
obsea-0.0.3.dist-info/LICENSE.txt
obsea-0.0.3.dist-info/METADATA
obsea-0.0.3.dist-info/WHEEL
obsea-0.0.3.dist-info/top_level.txt
obsea-0.0.3.dist-info/RECORD
