Metadata-Version: 2.1
Name: obsea
Version: 0.0.3
Summary: Metamorphoses Ocean-bottom seismometers into watchful observers of the Oceans.
Home-page: https://github.com/atrabattoni/obsea
Author: Alister Trabattoni
Author-email: alister.trabattoni@gmail.com
License: lgpl3
Project-URL: Documentation, https://pyscaffold.org/
Platform: any
Classifier: Development Status :: 4 - Beta
Classifier: Programming Language :: Python
Provides-Extra: testing
Requires-Dist: pytest ; extra == 'testing'
Requires-Dist: pytest-cov ; extra == 'testing'
